amgi_aiobotocore/__init__.py
amgi_aiobotocore/py.typed
amgi_aiobotocore/sqs.py
amgi_aiobotocore-0.32.0.dist-info/licenses/LICENSE
amgi_aiobotocore-0.32.0.dist-info/WHEEL
amgi_aiobotocore-0.32.0.dist-info/entry_points.txt
amgi_aiobotocore-0.32.0.dist-info/METADATA
amgi_aiobotocore-0.32.0.dist-info/RECORD
