Metadata-Version: 2.4
Name: amgi-aiobotocore
Version: 0.32.0
Summary: AMGI AWS Services Servers
Author: jack.burridge
Author-email: jack.burridge <jack.burridge@mail.com>
License-Expression: MIT
License-File: LICENSE
Classifier: Programming Language :: Python :: 3 :: Only
Classifier: Programming Language :: Python :: 3.10
Classifier: Programming Language :: Python :: 3.11
Classifier: Programming Language :: Python :: 3.12
Classifier: Programming Language :: Python :: 3.13
Classifier: Programming Language :: Python :: 3.14
Requires-Dist: aiobotocore>=2.25.0
Requires-Dist: amgi-common==0.32.0
Requires-Dist: amgi-types==0.32.0
Requires-Dist: typing-extensions>=4.15.0 ; python_full_version < '3.11'
Requires-Python: >=3.10
